aimesh/__init__.py
aimesh/core.py
aimesh-0.0.1.dist-info/LICENSE
aimesh-0.0.1.dist-info/METADATA
aimesh-0.0.1.dist-info/WHEEL
aimesh-0.0.1.dist-info/top_level.txt
aimesh-0.0.1.dist-info/RECORD
